knoxcraft/__init__.py
knoxcraft/terp.py
knoxcraft-0.0.1.dist-info/licenses/LICENSE
knoxcraft-0.0.1.dist-info/METADATA
knoxcraft-0.0.1.dist-info/WHEEL
knoxcraft-0.0.1.dist-info/top_level.txt
knoxcraft-0.0.1.dist-info/RECORD
